calculator.py
ecalculator_pkg_linda_oranya-0.0.4.dist-info/LICENSE
ecalculator_pkg_linda_oranya-0.0.4.dist-info/METADATA
ecalculator_pkg_linda_oranya-0.0.4.dist-info/WHEEL
ecalculator_pkg_linda_oranya-0.0.4.dist-info/top_level.txt
ecalculator_pkg_linda_oranya-0.0.4.dist-info/RECORD
