Metadata-Version: 2.1
Name: ecalculator-pkg-linda-oranya
Version: 0.0.4
Summary: A calculator written in python
Home-page: https://github.com/linda-oranya/pypi_calculator
Author: Linda Oranya
Author-email: oranyalinda7@gmail.com
License: UNKNOWN
Project-URL: Bug Tracker, https://github.com/linda-oranya/pypi_calculator/issues
Platform: UNKNOWN
Classifier: Programming Language :: Python :: 3
Classifier: License :: OSI Approved :: MIT License
Classifier: Operating System :: OS Independent
Requires-Python: >=3.6
